anyblok_mixins/__init__.py
anyblok_mixins/conftest.py
anyblok_mixins/release.py
anyblok_mixins/mixins/__init__.py
anyblok_mixins/mixins/basic.py
anyblok_mixins/mixins/exceptions.py
anyblok_mixins/mixins/readonly.py
anyblok_mixins/tests/__init__.py
anyblok_mixins/tests/conftest.py
anyblok_mixins/tests/test_mixin.py
anyblok_mixins/tests/test_workflow.py
anyblok_mixins/workflow/__init__.py
anyblok_mixins/workflow/exceptions.py
anyblok_mixins/workflow/marshmallow.py
anyblok_mixins/workflow/workflow.py
anyblok_mixins-1.0.2.dist-info/LICENSE
anyblok_mixins-1.0.2.dist-info/METADATA
anyblok_mixins-1.0.2.dist-info/WHEEL
anyblok_mixins-1.0.2.dist-info/entry_points.txt
anyblok_mixins-1.0.2.dist-info/top_level.txt
anyblok_mixins-1.0.2.dist-info/RECORD
